ossprey/__init__.py
ossprey/__main__.py
ossprey/args.py
ossprey/environment.py
ossprey/github_actions_reporter.py
ossprey/log.py
ossprey/main.py
ossprey/modes.py
ossprey/ossprey.py
ossprey/sbom_docker.py
ossprey/sbom_filesystem.py
ossprey/sbom_javascript.py
ossprey/sbom_python.py
ossprey/scan.py
ossprey/test_args.py
ossprey/test_github_actions_reporter.py
ossprey/test_main.py
ossprey/test_mode_fs.py
ossprey/test_sbom_filesystem.py
ossprey/test_sbom_javascript.py
ossprey/test_sbom_python.py
ossprey/test_scan.py
ossprey/test_virtualenv.py
ossprey/virtualenv.py
ossprey-1.0.18.dist-info/METADATA
ossprey-1.0.18.dist-info/WHEEL
ossprey-1.0.18.dist-info/entry_points.txt
ossprey-1.0.18.dist-info/licenses/LICENSE
ossprey-1.0.18.dist-info/RECORD
