Metadata-Version: 2.4
Name: ossprey
Version: 1.0.18
Summary: Ossprey tooling to scan your software package, create an SBOM and then submit it to our service for malware scanning
License: GPL-3.0
License-File: LICENSE
Author: dreadn0ught
Requires-Python: >=3.12,<4.0
Classifier: License :: OSI Approved :: GNU General Public License v3 (GPLv3)
Classifier: Programming Language :: Python :: 3
Classifier: Programming Language :: Python :: 3.12
Classifier: Programming Language :: Python :: 3.13
Classifier: Programming Language :: Python :: 3.14
Requires-Dist: cyclonedx-bom (>=5.1.1,<6.0.0)
Requires-Dist: cyclonedx-python-lib[json-validation] (>=8.4.0,<9.0.0)
Requires-Dist: ossbom (>=1.0.10,<2.0.0)
Requires-Dist: packageurl-python (>=0.16.0,<0.17.0)
Requires-Dist: pygithub (>=2.4.0,<3.0.0)
Requires-Dist: requests (>=2.32.3,<3.0.0)
